digest/__init__.py
digest-1.1.1.dist-info/LICENSE.md
digest-1.1.1.dist-info/METADATA
digest-1.1.1.dist-info/WHEEL
digest-1.1.1.dist-info/entry_points.txt
digest-1.1.1.dist-info/top_level.txt
digest-1.1.1.dist-info/RECORD
