Metadata-Version: 2.1
Name: digest
Version: 1.1.1
Summary: Calculate message digests of files or standard input
Home-page: http://software.clapper.org/digest/
Author: Brian M. Clapper
Author-email: bmc@clapper.org
License: Apache Software License Version 2.0
Classifier: Intended Audience :: Developers
Classifier: Intended Audience :: System Administrators
Classifier: License :: OSI Approved :: Apache Software License
Classifier: Programming Language :: Python
Classifier: Topic :: Text Processing :: Filters
Classifier: Topic :: Utilities
License-File: LICENSE.md
